MANIFEST.in
README.txt
setup.py
docs/HISTORY.txt
onegov/__init__.py
onegov.edu.egg-info/PKG-INFO
onegov.edu.egg-info/SOURCES.txt
onegov.edu.egg-info/dependency_links.txt
onegov.edu.egg-info/entry_points.txt
onegov.edu.egg-info/namespace_packages.txt
onegov.edu.egg-info/not-zip-safe
onegov.edu.egg-info/requires.txt
onegov.edu.egg-info/top_level.txt
onegov/edu/__init__.py
onegov/edu/configure.zcml
onegov/edu/inflator.zcml
onegov/edu/interfaces.py
onegov/edu/lawgiver.zcml
onegov/edu/setuphandlers.py
onegov/edu/testing.py
onegov/edu/browser/resources/logo_onegov.png
onegov/edu/locales/plone.pot
onegov/edu/locales/de/LC_MESSAGES/plone.po
onegov/edu/profiles/default/actions.xml
onegov/edu/profiles/default/browserlayer.xml
onegov/edu/profiles/default/metadata.xml
onegov/edu/profiles/default/onegov.edu-various.txt
onegov/edu/profiles/default/portal_placeful_workflow.xml
onegov/edu/profiles/default/propertiestool.xml
onegov/edu/profiles/default/tinymce.xml
onegov/edu/profiles/default/workflows.xml
onegov/edu/profiles/default/portal_placeful_workflow/onegovedu_workflow_policy.xml
onegov/edu/profiles/default/types/AddressBlock.xml
onegov/edu/profiles/default/types/ContentPage.xml
onegov/edu/profiles/default/types/EventFolder.xml
onegov/edu/profiles/default/types/EventPage.xml
onegov/edu/profiles/default/types/Folder.xml
onegov/edu/profiles/default/types/FormFolder.xml
onegov/edu/profiles/default/types/ListingBlock.xml
onegov/edu/profiles/default/types/News.xml
onegov/edu/profiles/default/types/NewsFolder.xml
onegov/edu/profiles/default/types/Plone_Site.xml
onegov/edu/profiles/default/types/TextBlock.xml
onegov/edu/profiles/default/workflows/onegov_edu_intranet_workflow/definition.xml
onegov/edu/profiles/default/workflows/onegov_edu_intranet_workflow/specification.txt
onegov/edu/profiles/default/workflows/onegov_edu_workflow/definition.xml
onegov/edu/profiles/default/workflows/onegov_edu_workflow/specification.txt
onegov/edu/profiles/init/metadata.xml
onegov/edu/profiles/init/portlets.xml
onegov/edu/profiles/init/properties.xml
onegov/edu/profiles/init/content_creation/10_welcome.json
onegov/edu/profiles/init/content_creation/11_impressum.json
onegov/edu/profiles/init/content_creation/12_internal.json
