Metadata-Version: 1.1
Name: onegov.edu
Version: 1.0.3
Summary: Policy package for OneGov.edu pages
Home-page: http://github.com/onegov/onegov.edu
Author: Verein OneGov
Author-email: mailto:info@4teamwork.ch
License: GPL2
Keywords: onegov edu plone
Platform: UNKNOWN
Classifier: Framework :: Plone
Classifier: Framework :: Plone :: 4.2
Classifier: Programming Language :: Python
